<?xml version="1.0" encoding="utf-8"?>
<abapGit version="v1.0.0" serializer="LCL_OBJECT_PINF" serializer_version="v1.0.0">
 <asx:abap xmlns:asx="http://www.sap.com/abapxml" version="1.0">
  <asx:values>
   <PINF>
    <ATTRIBUTES>
     <INTF_NAME>ZALOG_LOGGERS_PUBLIC</INTF_NAME>
     <DESCRIPT>ZALOG_LOGGERS public</DESCRIPT>
    </ATTRIBUTES>
    <ELEMENTS>
     <SCOMELDTLN>
      <INTF_NAME>ZALOG_LOGGERS_PUBLIC</INTF_NAME>
      <ELEM_TYPE>CLAS</ELEM_TYPE>
      <ELEM_KEY>ZCL_ALOG_ADT_LOGGER</ELEM_KEY>
     </SCOMELDTLN>
     <SCOMELDTLN>
      <INTF_NAME>ZALOG_LOGGERS_PUBLIC</INTF_NAME>
      <ELEM_TYPE>CLAS</ELEM_TYPE>
      <ELEM_KEY>ZCL_ALOG_BAL_LOGGER</ELEM_KEY>
     </SCOMELDTLN>
     <SCOMELDTLN>
      <INTF_NAME>ZALOG_LOGGERS_PUBLIC</INTF_NAME>
      <ELEM_TYPE>CLAS</ELEM_TYPE>
      <ELEM_KEY>ZCL_ALOG_DBTAB_LOGGER</ELEM_KEY>
     </SCOMELDTLN>
     <SCOMELDTLN>
      <INTF_NAME>ZALOG_LOGGERS_PUBLIC</INTF_NAME>
      <ELEM_TYPE>CLAS</ELEM_TYPE>
      <ELEM_KEY>ZCL_ALOG_DUMMY_LOGGER</ELEM_KEY>
     </SCOMELDTLN>
     <SCOMELDTLN>
      <INTF_NAME>ZALOG_LOGGERS_PUBLIC</INTF_NAME>
      <ELEM_TYPE>CLAS</ELEM_TYPE>
      <ELEM_KEY>ZCL_ALOG_FILE_LOGGER</ELEM_KEY>
     </SCOMELDTLN>
     <SCOMELDTLN>
      <INTF_NAME>ZALOG_LOGGERS_PUBLIC</INTF_NAME>
      <ELEM_TYPE>CLAS</ELEM_TYPE>
      <ELEM_KEY>ZCL_ALOG_ITAB_LOGGER</ELEM_KEY>
     </SCOMELDTLN>
     <SCOMELDTLN>
      <INTF_NAME>ZALOG_LOGGERS_PUBLIC</INTF_NAME>
      <ELEM_TYPE>CLAS</ELEM_TYPE>
      <ELEM_KEY>ZCL_ALOG_LOGGER_BASE</ELEM_KEY>
     </SCOMELDTLN>
     <SCOMELDTLN>
      <INTF_NAME>ZALOG_LOGGERS_PUBLIC</INTF_NAME>
      <ELEM_TYPE>CLAS</ELEM_TYPE>
      <ELEM_KEY>ZCL_ALOG_MESSAGE_LOGGER</ELEM_KEY>
     </SCOMELDTLN>
     <SCOMELDTLN>
      <INTF_NAME>ZALOG_LOGGERS_PUBLIC</INTF_NAME>
      <ELEM_TYPE>CLAS</ELEM_TYPE>
      <ELEM_KEY>ZCL_ALOG_MSG_LOGGER_BASE</ELEM_KEY>
     </SCOMELDTLN>
     <SCOMELDTLN>
      <INTF_NAME>ZALOG_LOGGERS_PUBLIC</INTF_NAME>
      <ELEM_TYPE>CLAS</ELEM_TYPE>
      <ELEM_KEY>ZCL_ALOG_PROGRESS_REP_LOGGER</ELEM_KEY>
     </SCOMELDTLN>
     <SCOMELDTLN>
      <INTF_NAME>ZALOG_LOGGERS_PUBLIC</INTF_NAME>
      <ELEM_TYPE>INTF</ELEM_TYPE>
      <ELEM_KEY>ZIF_ALOG_LOGGER</ELEM_KEY>
     </SCOMELDTLN>
     <SCOMELDTLN>
      <INTF_NAME>ZALOG_LOGGERS_PUBLIC</INTF_NAME>
      <ELEM_TYPE>INTF</ELEM_TYPE>
      <ELEM_KEY>ZIF_ALOG_MSG_LOGGER</ELEM_KEY>
     </SCOMELDTLN>
    </ELEMENTS>
   </PINF>
  </asx:values>
 </asx:abap>
</abapGit>
